odoo/addons/hr_payroll_account_operating_unit/README.rst
odoo/addons/hr_payroll_account_operating_unit/__init__.py
odoo/addons/hr_payroll_account_operating_unit/__manifest__.py
odoo/addons/hr_payroll_account_operating_unit/i18n/hr_payroll_account_operating_unit.pot
odoo/addons/hr_payroll_account_operating_unit/i18n/it.po
odoo/addons/hr_payroll_account_operating_unit/i18n/pt.po
odoo/addons/hr_payroll_account_operating_unit/models/__init__.py
odoo/addons/hr_payroll_account_operating_unit/models/account_move.py
odoo/addons/hr_payroll_account_operating_unit/models/hr_payslip.py
odoo/addons/hr_payroll_account_operating_unit/readme/CONTRIBUTORS.rst
odoo/addons/hr_payroll_account_operating_unit/readme/DESCRIPTION.rst
odoo/addons/hr_payroll_account_operating_unit/static/description/icon.png
odoo/addons/hr_payroll_account_operating_unit/static/description/index.html
odoo/addons/hr_payroll_account_operating_unit/tests/__init__.py
odoo/addons/hr_payroll_account_operating_unit/tests/test_payroll_account_operating_unit.py
odoo14_addon_hr_payroll_account_operating_unit-14.0.1.0.1.dev10.dist-info/METADATA
odoo14_addon_hr_payroll_account_operating_unit-14.0.1.0.1.dev10.dist-info/WHEEL
odoo14_addon_hr_payroll_account_operating_unit-14.0.1.0.1.dev10.dist-info/top_level.txt
odoo14_addon_hr_payroll_account_operating_unit-14.0.1.0.1.dev10.dist-info/RECORD
